predictions_sepsis/__init__.py
predictions_sepsis/balance_on_patients.py
predictions_sepsis/choose.py
predictions_sepsis/combine_diagnoses_and_ssir.py
predictions_sepsis/compress.py
predictions_sepsis/fill_values.py
predictions_sepsis/get_diagnoses.py
predictions_sepsis/get_disease_info.py
predictions_sepsis/get_ssir.py
predictions_sepsis/merge_diagnoses_and_ssir_with_blood.py
predictions_sepsis/train_model.py
predictions_sepsis/transformers.py
predictions_sepsis-1.0.4.dist-info/METADATA
predictions_sepsis-1.0.4.dist-info/WHEEL
predictions_sepsis-1.0.4.dist-info/top_level.txt
predictions_sepsis-1.0.4.dist-info/RECORD
