Metadata-Version: 2.1
Name: predictions-sepsis
Version: 1.0.4
Summary: Module for sepsis predictions
Home-page: https://github.com/sslavian812/sepsis-predictions.git
Author: @Margo78, @akp1n
Author-email: timtimk30@yandex.ru
License: UNKNOWN
Keywords: sepsis,predictions,python
Platform: UNKNOWN
Classifier: Programming Language :: Python :: 3.11
Classifier: License :: OSI Approved :: MIT License
Classifier: Operating System :: OS Independent
Requires-Python: >=3.7
Requires-Dist: requests (>=2.25.1)
Requires-Dist: pandas (>=1.3.3)
Requires-Dist: tqdm (>=4.62.3)
Requires-Dist: numpy (>=1.21.2)
Requires-Dist: scikit-learn (>=0.24.2)
Requires-Dist: imbalanced-learn (>=0.8.0)
Requires-Dist: pytorch-tabnet (>=3.1.1)
Requires-Dist: torch (>=1.9.0)
Requires-Dist: nona (>=0.0.2)
